<storia>
        <cing1>
                <segmento>2</segmento>
                <messaggio>Growl</messaggio>
                <messaggio>growl...</messaggio> 
        </cing1>
        <interlocutore>
                <segmento>2</segmento>
                <messaggio>Esci muoviti! Il califfo sta parlando e manchi solo tu!</messaggio>
                <messaggio>Se non vai sarai messo al bando</messaggio>
                <messaggio>Tutti devono essere presenti!</messaggio>
                <messaggio>Sbrigati!</messaggio>
        </interlocutore>
        <interlocutore1>
                <segmento>1</segmento>
                <messaggio>uno di uno</messaggio>
        </interlocutore1>
         <villager>
                <segmento>1</segmento>
                <messaggio>Seguimi!</messaggio>
        </villager>
        <aio>
                <segmento>1</segmento>
                <messaggio>Le tasse sono state alzate ancora!</messaggio>
                <messaggio>E' inutile che vi lamentiate</messaggio>
                <messaggio>Se non pagate morirete!</messaggio>
        </aio>
</storia>